tensorflowlitex/__init__.py
tensorflowlitex/binary_loader.py
tensorflowlitex/runtime_hook.py
TensorFlowLiteX-0.1.7.dist-info/METADATA
TensorFlowLiteX-0.1.7.dist-info/WHEEL
TensorFlowLiteX-0.1.7.dist-info/entry_points.txt
TensorFlowLiteX-0.1.7.dist-info/top_level.txt
TensorFlowLiteX-0.1.7.dist-info/RECORD
